diddiparser/__init__.py
diddiparser/__main__.py
diddiparser/main.py
diddiparser/parser.py
diddiparser/lib/__init__.py
diddiparser/lib/diddi_stdfuncs.py
diddiparser/lib/lang_runners.py
diddiparser-1.3.dist-info/LICENSE
diddiparser-1.3.dist-info/METADATA
diddiparser-1.3.dist-info/WHEEL
diddiparser-1.3.dist-info/entry_points.txt
diddiparser-1.3.dist-info/top_level.txt
diddiparser-1.3.dist-info/RECORD
