Metadata-Version: 2.1
Name: diddiparser
Version: 1.3
Summary: Parser for DiddiScript files.
Home-page: https://github.com/diddileija/diddiparser/blob/main/README.md
Author: Diego Ramirez
Author-email: dr01191115@gmail.com
License: MIT
Project-URL: Documentation, http://github.com/diddileija/diddiparser/blob/main/README.md
Project-URL: Tracker, http://github.com/diddileija/diddiparser/issues
Keywords: diddi diddiscript script files parse python
Platform: UNKNOWN
Classifier: Development Status :: 5 - Production/Stable
Classifier: Intended Audience :: Developers
Classifier: Natural Language :: English
Classifier: Programming Language :: Python :: 3
Classifier: Programming Language :: Python :: 3.6
Classifier: Programming Language :: Python :: 3.7
Classifier: Programming Language :: Python :: 3.8
Classifier: Programming Language :: Python :: 3.9
Classifier: License :: OSI Approved :: MIT License
Classifier: Operating System :: Microsoft
Classifier: Operating System :: Microsoft :: Windows
Classifier: Operating System :: Microsoft :: Windows :: Windows 7
Classifier: Operating System :: Microsoft :: Windows :: Windows 8
Classifier: Topic :: Software Development
Requires-Python: >=3.6, <3.10
License-File: LICENSE
Requires-Dist: colorama
